fakerx/__init__.py
fakerx/fakerx.py
fakerx-0.2.0.dist-info/licenses/LICENSE
fakerx-0.2.0.dist-info/METADATA
fakerx-0.2.0.dist-info/WHEEL
fakerx-0.2.0.dist-info/entry_points.txt
fakerx-0.2.0.dist-info/top_level.txt
fakerx-0.2.0.dist-info/RECORD
