Metadata-Version: 2.4
Name: fakerx
Version: 0.2.0
Summary: 强大的Python数据生成库，Faker的增强版
Author-email: YingZi <yxdszlkc@163.com>
License: MIT
Project-URL: Homepage, https://github.com/yourusername/fakerx
Project-URL: Repository, https://github.com/yourusername/fakerx
Classifier: Development Status :: 4 - Beta
Classifier: Intended Audience :: Developers
Classifier: License :: OSI Approved :: MIT License
Classifier: Operating System :: OS Independent
Classifier: Programming Language :: Python :: 3
Classifier: Programming Language :: Python :: 3.8
Classifier: Programming Language :: Python :: 3.9
Classifier: Programming Language :: Python :: 3.10
Classifier: Programming Language :: Python :: 3.11
Classifier: Programming Language :: Python :: 3.12
Classifier: Programming Language :: Python :: 3.13
Requires-Python: >=3.8
License-File: LICENSE
Requires-Dist: faker
Requires-Dist: pydantic
Requires-Dist: pydantic[email]
Requires-Dist: pyyaml
Dynamic: license-file
